multisite/__init__.py
multisite/__main__.py
multisite-0.1.0.dist-info/METADATA
multisite-0.1.0.dist-info/RECORD
multisite-0.1.0.dist-info/WHEEL
multisite-0.1.0.dist-info/entry_points.txt
multisite-0.1.0.dist-info/top_level.txt
