Metadata-Version: 2.1
Name: multisite
Version: 0.1.0
Summary: Host multiple standalone websites under a single site
Home-page: https://github.com/cmccandless/multisite
Author: Corey McCandless
Author-email: crm1994@gmail.com
License: UNKNOWN
Platform: UNKNOWN
Classifier: Programming Language :: Python :: 3
Classifier: License :: OSI Approved :: MIT License
Classifier: Operating System :: OS Independent
Requires-Dist: argutil
